mlagents_sps_plugin/__init__.py
mlagents_sps_plugin/sps_stats_writer.py
mlagents_sps_plugin-0.1.0.dist-info/LICENSE
mlagents_sps_plugin-0.1.0.dist-info/METADATA
mlagents_sps_plugin-0.1.0.dist-info/WHEEL
mlagents_sps_plugin-0.1.0.dist-info/entry_points.txt
mlagents_sps_plugin-0.1.0.dist-info/top_level.txt
mlagents_sps_plugin-0.1.0.dist-info/RECORD
