Metadata-Version: 2.1
Name: mlagents_sps_plugin
Version: 0.1.0
Summary: A plugin for Unity ML-Agents to log Steps Per Second (SPS) to TensorBoard
Home-page: https://github.com/louisgthier/mlagents-sps-plugin
Author: Louis Gauthier
Author-email: louis@dgwave.net
Classifier: Programming Language :: Python :: 3
Classifier: License :: OSI Approved :: MIT License
Classifier: Intended Audience :: Developers
Classifier: Topic :: Scientific/Engineering :: Artificial Intelligence
Requires-Python: >=3.6
License-File: LICENSE
Requires-Dist: mlagents >=0.30.0
Requires-Dist: torch
Requires-Dist: tensorboard
